{"cameraMode":{"drawMode":0,"name":"Shaded","section":"Shading Mode"},"sceneLighting":true,"audioPlay":false,"sceneViewState":{"showFog":true,"showMaterialUpdate":false,"showSkybox":true,"showFlares":true,"showImageEffects":true,"showParticleSystems":true},"in2DMode":false,"pivot":{"x":-1290.140625,"y":542.8016357421875,"z":148.02960205078126},"rotation":{"x":-0.000695057853590697,"y":-0.9990711808204651,"z":0.03929300978779793,"w":-0.017679013311862947},"size":2321.690185546875,"orthographic":false}